{
  "name": "FL Studio API Stubs",
  "description": "Type definitions, and full documentation for FL Studio's MIDI Controller Scripting API",
  "color": "#ff6600",
  "sort": 6,
  "links": {
    "repo": {
      "provider": "github",
      "path": "IL-Group/FL-Studio-API-Stubs"
    },
    "docs": "https://il-group.github.io/FL-Studio-API-Stubs/"
  },
  "package": {
    "provider": "pypi",
    "id": "fl-studio-api-stubs"
  },
  "associations": {
    "languages": [
      "python"
    ],
    "frameworks": [
      "midi-controller-scripting",
      "mkdocs",
      "mypy"
    ],
    "skills": [
      "midi",
      "documentation",
      "packages"
    ],
    "status": [
      "active"
    ]
  },
  "icon": "icon.png",
  "banner": "banner.png"
}
